nexusflowmeter/__init__.py
nexusflowmeter/cli.py
nexusflowmeter/converter.py
nexusflowmeter-0.1.5.dist-info/licenses/LICENSE
nexusflowmeter-0.1.5.dist-info/METADATA
nexusflowmeter-0.1.5.dist-info/WHEEL
nexusflowmeter-0.1.5.dist-info/entry_points.txt
nexusflowmeter-0.1.5.dist-info/top_level.txt
nexusflowmeter-0.1.5.dist-info/RECORD
