Metadata-Version: 2.4
Name: nexusflowmeter
Version: 0.1.5
Summary: Convert PCAP files to flow-based analysis (CSV, JSON, Excel)
Author-email: Ashwin <ashwinkulkarni737@gmail.com>
License: MIT License
Requires-Python: >=3.8
License-File: LICENSE
Requires-Dist: scapy
Requires-Dist: pandas
Requires-Dist: openpyxl
Dynamic: license-file
